darkhex/__init__.py
darkhex/darkhextools.py
darkhex/algorithms/__init__.py
darkhex/algorithms/best_response.py
darkhex/algorithms/examine_result.py
darkhex/algorithms/generate_info_states.py
darkhex/algorithms/pone.py
darkhex/algorithms/pone_v1.py
darkhex/algorithms/tree_generator.py
darkhex/algorithms/tree_run.py
darkhex/utils/__init__.py
darkhex/utils/cPlot.py
darkhex/utils/colors.py
darkhex/utils/curses_func.py
darkhex/utils/drive.py
darkhex/utils/isomorphic.py
darkhex/utils/pit.py
darkhex/utils/print_tools.py
darkhex/utils/util.py
darkhex-0.0.1.dist-info/LICENSE
darkhex-0.0.1.dist-info/METADATA
darkhex-0.0.1.dist-info/WHEEL
darkhex-0.0.1.dist-info/top_level.txt
darkhex-0.0.1.dist-info/RECORD
