Metadata-Version: 2.1
Name: darkhex
Version: 0.0.1
Summary: Set of tools to analyze and research the game Dark Hex.
Home-page: https://github.com/BedirT/darkHex
Author: Bedir Tapkan
Author-email: tapkan@ualberta.ca
License: UNKNOWN
Project-URL: Bug Reports, https://github.com/BedirT/darkHex/issues
Platform: UNKNOWN
Classifier: Development Status :: 2 - Pre-Alpha
Classifier: Environment :: Console
Classifier: Intended Audience :: Science/Research
Classifier: License :: OSI Approved :: MIT License
Classifier: Topic :: Games/Entertainment :: Board Games
Classifier: Topic :: Scientific/Engineering :: Artificial Intelligence
Classifier: Operating System :: OS Independent
Classifier: Programming Language :: Python :: 3
Requires-Python: >=3.6
License-File: LICENSE
Requires-Dist: numpy
Requires-Dist: open-spiel
Requires-Dist: pydot
Requires-Dist: xdot
Requires-Dist: pycairo
Requires-Dist: PyGObject
Requires-Dist: dill
Provides-Extra: dev
Requires-Dist: pytest ; extra == 'dev'
Requires-Dist: typing ; extra == 'dev'
